allitnil/__init__.py
allitnil-0.0.0.dist-info/METADATA
allitnil-0.0.0.dist-info/WHEEL
allitnil-0.0.0.dist-info/top_level.txt
allitnil-0.0.0.dist-info/RECORD
