Metadata-Version: 2.1
Name: allitnil
Version: 0.0.0
Summary: place holder
Home-page: http://github.com/SK/allitnil
License: MIT
